Workbook
Name ROI: Project_Pipeline_Model!$I$13:$I$23

Sheet Model_Assumptions
A1: PARAMETER | B1: VALUE
A2: FINANCIAL ASSUMPTIONS
A3: Low Budget | B3: 1500000
A4: Mid Budget | B4: 6000000
A5: High Budget | B5: 25000000
A6: Avg Theatre Ticket Price | B6: 500
A7: Avg Streaming Rights Revenue | B7: 40000000
A8: Avg Sponsorship Revenue | B8: 1000000
A9: OPERATIONAL ASSUMPTIONS
A10: Avg Theatre Audience per show | B10: 400
A11: Avg No. of Shows per Theatre Project | B11: 20
A13: Budget Type | B13: Budget Value
A14: Low | B14: 1500000
A15: Mid | B15: 6000000
A16: High | B16: 25000000

Sheet Project_Pipeline_Model
F1: All financial figures in INR
F2: OBSCURE PRODUCTION — PROJECT DECISION SUMMARY
F3: Key Insights:
F4: • Streaming generates ₹10.2 Cr total profit with 324% average ROI
F5: • Theatre generates ₹1.2 Cr profit with lower ROI (150%)
F6: • Two theatre projects generate negative ROI (-16.67%)
F7: • Streaming shows higher profit volatility due to larger budgets
F8: Strategic Recommendation:
F9: • Increase capital allocation toward Streaming
F10: • Strengthen greenlight criteria for Theatre projects
F11: • Maintain a hybrid strategy across Streaming and Theatre
A13: PROJECT_ID | B13: PROJECT_NAME | C13: GENRE | D13: FORMAT | E13: BUDGET_TYPE | F13: Planned Budget | G13: Estimated Revenue | H13: Profit | I13: ROI % | J13: Top Performer | K13: Status | L13: Analysis | M13: Value
A14: P001 | B14: Echoes in the Dark | C14: Horror | D14: Theatre | E14: Low | F14: =_xlfn.XLOOKUP(Project_Pipeline_Model!$E14,tbl_budget[Budget Type],tbl_budget[Budget Value]) -> 1500000 | G14: =IF(Project_Pipeline_Model!$D14="Theatre", (Model_Assumptions!$B$6*Model_Assumptions!$B$10*Model_Assumptions!$B$11)+Model_Assumptions!$B$8, Model_Assumptions!$B$7+Model_Assumptions!$B$8) -> 5000000 | H14: =Project_Pipeline_Model!$G14-Project_Pipeline_Model!$F14 -> 3500000 | I14: =Project_Pipeline_Model!$H14/Project_Pipeline_Model!$F14 -> 2.3333333 | J14: =IF(Project_Pipeline_Model!$I14=MAX(ROI),"Top Performer","") | K14: =IF(Project_Pipeline_Model!$H14>0,"Go","Review") -> Go
A15: P002 | B15: Veil of Silence | C15: Thriller | D15: Streaming | E15: High | F15: =_xlfn.XLOOKUP(Project_Pipeline_Model!$E15,tbl_budget[Budget Type],tbl_budget[Budget Value]) -> 25000000 | G15: =IF(Project_Pipeline_Model!$D15="Theatre", (Model_Assumptions!$B$6*Model_Assumptions!$B$10*Model_Assumptions!$B$11)+Model_Assumptions!$B$8, Model_Assumptions!$B$7+Model_Assumptions!$B$8) -> 41000000 | H15: =Project_Pipeline_Model!$G15-Project_Pipeline_Model!$F15 -> 16000000 | I15: =Project_Pipeline_Model!$H15/Project_Pipeline_Model!$F15 -> 0.64 | J15: =IF(Project_Pipeline_Model!$I15=MAX(ROI),"Top Performer","") | K15: =IF(Project_Pipeline_Model!$H15>0,"Go","Review") -> Go | L15: Metric | M15: Value
A16: P003 | B16: The Hollow Room | C16: Horror | D16: Theatre | E16: Low | F16: =_xlfn.XLOOKUP(Project_Pipeline_Model!$E16,tbl_budget[Budget Type],tbl_budget[Budget Value]) -> 1500000 | G16: =IF(Project_Pipeline_Model!$D16="Theatre", (Model_Assumptions!$B$6*Model_Assumptions!$B$10*Model_Assumptions!$B$11)+Model_Assumptions!$B$8, Model_Assumptions!$B$7+Model_Assumptions!$B$8) -> 5000000 | H16: =Project_Pipeline_Model!$G16-Project_Pipeline_Model!$F16 -> 3500000 | I16: =Project_Pipeline_Model!$H16/Project_Pipeline_Model!$F16 -> 2.3333333 | J16: =IF(Project_Pipeline_Model!$I16=MAX(ROI),"Top Performer","") | K16: =IF(Project_Pipeline_Model!$H16>0,"Go","Review") -> Go | L16: Total Projects | M16: =COUNTA(Project_Pipeline_Model!$B$14:$B$36) -> 10
A17: P004 | B17: Fractured Mind | C17: Thriller | D17: Streaming | E17: Mid | F17: =_xlfn.XLOOKUP(Project_Pipeline_Model!$E17,tbl_budget[Budget Type],tbl_budget[Budget Value]) -> 6000000 | G17: =IF(Project_Pipeline_Model!$D17="Theatre", (Model_Assumptions!$B$6*Model_Assumptions!$B$10*Model_Assumptions!$B$11)+Model_Assumptions!$B$8, Model_Assumptions!$B$7+Model_Assumptions!$B$8) -> 41000000 | H17: =Project_Pipeline_Model!$G17-Project_Pipeline_Model!$F17 -> 35000000 | I17: =Project_Pipeline_Model!$H17/Project_Pipeline_Model!$F17 -> 5.8333333 | J17: =IF(Project_Pipeline_Model!$I17=MAX(ROI),"Top Performer","") -> Top Performer | K17: =IF(Project_Pipeline_Model!$H17>0,"Go","Review") -> Go | L17: Projects to Review | M17: =COUNTIF(Project_Pipeline_Model!$K$14:$K$36,"Review") -> 2
A18: P005 | B18: The Unseen Corridor | C18: Horror | D18: Theatre | E18: Mid | F18: =_xlfn.XLOOKUP(Project_Pipeline_Model!$E18,tbl_budget[Budget Type],tbl_budget[Budget Value]) -> 6000000 | G18: =IF(Project_Pipeline_Model!$D18="Theatre", (Model_Assumptions!$B$6*Model_Assumptions!$B$10*Model_Assumptions!$B$11)+Model_Assumptions!$B$8, Model_Assumptions!$B$7+Model_Assumptions!$B$8) -> 5000000 | H18: =Project_Pipeline_Model!$G18-Project_Pipeline_Model!$F18 -> -1000000 | I18: =Project_Pipeline_Model!$H18/Project_Pipeline_Model!$F18 -> -0.16666667 | J18: =IF(Project_Pipeline_Model!$I18=MAX(ROI),"Top Performer","") | K18: =IF(Project_Pipeline_Model!$H18>0,"Go","Review") -> Review | L18: Average Profit | M18: =AVERAGE(Project_Pipeline_Model!$H$14:$H$36)/10000000 -> 1.14
A19: P006 | B19: Night Without Sound | C19: Horror | D19: Theatre | E19: Low | F19: =_xlfn.XLOOKUP(Project_Pipeline_Model!$E19,tbl_budget[Budget Type],tbl_budget[Budget Value]) -> 1500000 | G19: =IF(Project_Pipeline_Model!$D19="Theatre", (Model_Assumptions!$B$6*Model_Assumptions!$B$10*Model_Assumptions!$B$11)+Model_Assumptions!$B$8, Model_Assumptions!$B$7+Model_Assumptions!$B$8) -> 5000000 | H19: =Project_Pipeline_Model!$G19-Project_Pipeline_Model!$F19 -> 3500000 | I19: =Project_Pipeline_Model!$H19/Project_Pipeline_Model!$F19 -> 2.3333333 | J19: =IF(Project_Pipeline_Model!$I19=MAX(ROI),"Top Performer","") | K19: =IF(Project_Pipeline_Model!$H19>0,"Go","Review") -> Go | L19: Total Profit | M19: =SUM(Project_Pipeline_Model!$H$14:$H$36)/10000000 -> 11.4
A20: P007 | B20: Shattered Pulse | C20: Thriller | D20: Streaming | E20: Mid | F20: =_xlfn.XLOOKUP(Project_Pipeline_Model!$E20,tbl_budget[Budget Type],tbl_budget[Budget Value]) -> 6000000 | G20: =IF(Project_Pipeline_Model!$D20="Theatre", (Model_Assumptions!$B$6*Model_Assumptions!$B$10*Model_Assumptions!$B$11)+Model_Assumptions!$B$8, Model_Assumptions!$B$7+Model_Assumptions!$B$8) -> 41000000 | H20: =Project_Pipeline_Model!$G20-Project_Pipeline_Model!$F20 -> 35000000 | I20: =Project_Pipeline_Model!$H20/Project_Pipeline_Model!$F20 -> 5.8333333 | J20: =IF(Project_Pipeline_Model!$I20=MAX(ROI),"Top Performer","") -> Top Performer | K20: =IF(Project_Pipeline_Model!$H20>0,"Go","Review") -> Go | L20: Profit Volatility
A21: P008 | B21: The Final Frame | C21: Horror | D21: Theatre | E21: Mid | F21: =_xlfn.XLOOKUP(Project_Pipeline_Model!$E21,tbl_budget[Budget Type],tbl_budget[Budget Value]) -> 6000000 | G21: =IF(Project_Pipeline_Model!$D21="Theatre", (Model_Assumptions!$B$6*Model_Assumptions!$B$10*Model_Assumptions!$B$11)+Model_Assumptions!$B$8, Model_Assumptions!$B$7+Model_Assumptions!$B$8) -> 5000000 | H21: =Project_Pipeline_Model!$G21-Project_Pipeline_Model!$F21 -> -1000000 | I21: =Project_Pipeline_Model!$H21/Project_Pipeline_Model!$F21 -> -0.16666667 | J21: =IF(Project_Pipeline_Model!$I21=MAX(ROI),"Top Performer","") | K21: =IF(Project_Pipeline_Model!$H21>0,"Go","Review") -> Review | L21: Genre Profit (Horror) | M21: =SUMIF(Project_Pipeline_Model!$C$14:$C$36,"Horror",Project_Pipeline_Model!$H$14:$H$36)/10000000 -> 1.2
A22: P009 | B22: Beneath the Static | C22: Thriller | D22: Streaming | E22: High | F22: =_xlfn.XLOOKUP(Project_Pipeline_Model!$E22,tbl_budget[Budget Type],tbl_budget[Budget Value]) -> 25000000 | G22: =IF(Project_Pipeline_Model!$D22="Theatre", (Model_Assumptions!$B$6*Model_Assumptions!$B$10*Model_Assumptions!$B$11)+Model_Assumptions!$B$8, Model_Assumptions!$B$7+Model_Assumptions!$B$8) -> 41000000 | H22: =Project_Pipeline_Model!$G22-Project_Pipeline_Model!$F22 -> 16000000 | I22: =Project_Pipeline_Model!$H22/Project_Pipeline_Model!$F22 -> 0.64 | J22: =IF(Project_Pipeline_Model!$I22=MAX(ROI),"Top Performer","") | K22: =IF(Project_Pipeline_Model!$H22>0,"Go","Review") -> Go | L22: Genre Profit (Thriller) | M22: =SUMIF(Project_Pipeline_Model!$C$14:$C$36,"Thriller",Project_Pipeline_Model!$H$14:$H$36)/10000000 -> 10.2
A23: P010 | B23: Crimson Exit | C23: Horror | D23: Theatre | E23: Low | F23: =_xlfn.XLOOKUP(Project_Pipeline_Model!$E23,tbl_budget[Budget Type],tbl_budget[Budget Value]) -> 1500000 | G23: =IF(Project_Pipeline_Model!$D23="Theatre", (Model_Assumptions!$B$6*Model_Assumptions!$B$10*Model_Assumptions!$B$11)+Model_Assumptions!$B$8, Model_Assumptions!$B$7+Model_Assumptions!$B$8) -> 5000000 | H23: =Project_Pipeline_Model!$G23-Project_Pipeline_Model!$F23 -> 3500000 | I23: =Project_Pipeline_Model!$H23/Project_Pipeline_Model!$F23 -> 2.3333333 | J23: =IF(Project_Pipeline_Model!$I23=MAX(ROI),"Top Performer","") | K23: =IF(Project_Pipeline_Model!$H23>0,"Go","Review") -> Go | L23: Average ROI (Horror) | M23: =AVERAGEIF(Project_Pipeline_Model!$C$14:$C$36,"Horror",Project_Pipeline_Model!$I$14:$I$36) -> 1.5
J24: =IF(Project_Pipeline_Model!$I24=MAX(ROI),"Top Performer","") | L24: Average ROI (Thriller) | M24: =AVERAGEIF(Project_Pipeline_Model!$C$14:$C$36,"Thriller",Project_Pipeline_Model!$I$14:$I$36) -> 3.2366667
L25: Average ROI (Theatre) | M25: =AVERAGEIF(Project_Pipeline_Model!$D$14:$D$36,"Theatre",Project_Pipeline_Model!$I$14:$I$36) -> 1.5
L26: Average ROI (Streaming) | M26: =AVERAGEIF(Project_Pipeline_Model!$D$14:$D$36,"Streaming",Project_Pipeline_Model!$I$14:$I$36) -> 3.2366667
L27: Total Profit (Theatre) | M27: =SUMIF(Project_Pipeline_Model!$D$14:$D$36,"Theatre",Project_Pipeline_Model!$H$14:$H$36)/10000000 -> 1.2
L28: Total Profit (Streaming) | M28: =SUMIF(D14:D23,"Streaming",H14:H23)/10000000 -> 10.2
L29: Project Count (Theatre) | M29: =COUNTIF(Project_Pipeline_Model!$D$14:$D$36,"Theatre") -> 6
L30: Project Count (Streaming) | M30: =COUNTIF(Project_Pipeline_Model!$D$14:$D$36,"Streaming") -> 4
L31: Profit Volatility (Theatre) | M31: {=_xlfn.STDEV.S(IF(D14:D23="Theatre",H14:H23))/10000000} -> 0.232379
L32: Profit Volatility (Streaming) | M32: {=_xlfn.STDEV.S(IF(D14:D23="Streaming",H14:H23))/10000000} -> 1.0969655
L33: Best Project (ROI) | M33: =INDEX(B13:B22, MATCH(MAX(I13:I22), I13:I22, 0)) -> Fractured Mind
L34: Worst Project (ROI) | M34: =INDEX(B13:B22, MATCH(MIN(I13:I22), I13:I22, 0)) -> The Unseen Corridor

Sheet Executive_Dashboard
E1: OBSCURE PRODUCTIONS - PROJECT PERFORMANCE DASHBOARD
A3: FORMAT | B3: ROI
A4: Theatre | B4: 1.5
A5: Streaming | B5: 3.24
A8: GENRE | B8: PROFIT
A9: Horror | B9: 1.2
A10: Thriller | B10: 10.2
A13: STATUS | B13: COUNT
A14: Go | B14: 8
A15: Review | B15: 2
